MetroValencia-1.2.1.data/scripts/metrovalencia_cli
metrovalencia/__init__.py
metrovalencia/metrovalencia.py
MetroValencia-1.2.1.dist-info/LICENSE
MetroValencia-1.2.1.dist-info/METADATA
MetroValencia-1.2.1.dist-info/WHEEL
MetroValencia-1.2.1.dist-info/top_level.txt
MetroValencia-1.2.1.dist-info/RECORD
